paystack4python/__init__.py
paystack4python/baseapi.py
paystack4python/customers.py
paystack4python/errors.py
paystack4python/plans.py
paystack4python/transactions.py
paystack4python/utils.py
paystack4python/version.py
paystack4python-1.1.dist-info/licenses/LICENCE
paystack4python-1.1.dist-info/METADATA
paystack4python-1.1.dist-info/WHEEL
paystack4python-1.1.dist-info/top_level.txt
paystack4python-1.1.dist-info/RECORD
