Metadata-Version: 2.4
Name: paystack4python
Version: 1.1
Summary: Python wrapper for Paystack API
Home-page: https://github.com/mwaiseghegift/paystack4python
Author: Gift Mwaiseghe
Author-email: mwaiseghe.dev@gmail.com
License: MIT
License-File: LICENCE
Requires-Dist: requests
Dynamic: author
Dynamic: author-email
Dynamic: description
Dynamic: description-content-type
Dynamic: home-page
Dynamic: license
Dynamic: license-file
Dynamic: requires-dist
Dynamic: summary
